arc4.cpython-39-x86_64-linux-gnu.so
arc4-0.4.0.dist-info/WHEEL
arc4-0.4.0.dist-info/LICENSE
arc4-0.4.0.dist-info/RECORD
arc4-0.4.0.dist-info/METADATA
arc4-0.4.0.dist-info/top_level.txt
arc4-stubs/__init__.pyi
