Metadata-Version: 2.1
Name: arc4
Version: 0.4.0
Summary: A small and insanely fast ARCFOUR (RC4) cipher implementation of Python
Home-page: https://github.com/manicmaniac/arc4
Author: Ryosuke Ito
Author-email: rito.0305@gmail.com
License: UNKNOWN
Keywords: ARCFOUR,cipher,cryptography,RC4
Platform: UNKNOWN
Classifier: Development Status :: 4 - Beta
Classifier: License :: OSI Approved :: MIT License
Classifier: Operating System :: OS Independent
Classifier: Programming Language :: Python :: 3.7
Classifier: Programming Language :: Python :: 3.8
Classifier: Programming Language :: Python :: 3.9
Classifier: Programming Language :: Python :: 3.10
Classifier: Programming Language :: Python :: 3.11
Classifier: Programming Language :: Python :: Implementation :: CPython
Classifier: Programming Language :: Python :: Implementation :: PyPy
Classifier: Topic :: Security :: Cryptography
License-File: LICENSE
